gotenberg_client/__init__.py
gotenberg_client/api/__init__.py
gotenberg_client/api/chromium/__init__.py
gotenberg_client/api/chromium/post_forms_chromium_convert_html.py
gotenberg_client/api/chromium/post_forms_chromium_convert_markdown.py
gotenberg_client/api/chromium/post_forms_chromium_convert_url.py
gotenberg_client/api/libreoffice/__init__.py
gotenberg_client/api/libreoffice/post_forms_libreoffice_convert.py
gotenberg_client/api/pdfengines/__init__.py
gotenberg_client/api/pdfengines/post_forms_pdfengines_convert.py
gotenberg_client/api/pdfengines/post_forms_pdfengines_merge.py
gotenberg_client/client.py
gotenberg_client/models/__init__.py
gotenberg_client/models/html_conversion_request_body.py
gotenberg_client/models/markdown_conversion_request_body.py
gotenberg_client/models/merge_files_request_body.py
gotenberg_client/models/office_conversion_request_body.py
gotenberg_client/models/post_forms_pdfengines_convert_multipart_data.py
gotenberg_client/models/post_forms_pdfengines_merge_multipart_data.py
gotenberg_client/models/url_conversion_request_body.py
gotenberg_client/py.typed
gotenberg_client/types.py
gotenberg_client-7.0.0.dist-info/LICENSE
gotenberg_client-7.0.0.dist-info/WHEEL
gotenberg_client-7.0.0.dist-info/METADATA
gotenberg_client-7.0.0.dist-info/RECORD
