Metadata-Version: 2.1
Name: gotenberg-client
Version: 7.0.0
Summary: A client library for accessing Gotenberg
Home-page: https://github.com/matyasrichter/gotenberg-client-python
License: MIT
Keywords: gotenberg,api client,generated
Author: Matyas Richter
Author-email: matyas@mrichter.cz
Requires-Python: >=3.7,<4.0
Classifier: License :: OSI Approved :: MIT License
Classifier: Programming Language :: Python :: 3
Classifier: Programming Language :: Python :: 3.10
Classifier: Programming Language :: Python :: 3.7
Classifier: Programming Language :: Python :: 3.8
Classifier: Programming Language :: Python :: 3.9
Classifier: Topic :: Software Development :: Libraries
Classifier: Topic :: Software Development :: Libraries :: Python Modules
Classifier: Topic :: Utilities
Classifier: Typing :: Typed
Requires-Dist: attrs (>=21.3.0)
Requires-Dist: httpx (>=0.15.4,<0.23.0)
Requires-Dist: python-dateutil (>=2.8.0,<3.0.0)
